splunkhecwriter/__init__.py
splunkhecwriter-0.4.dist-info/LICENSE.md
splunkhecwriter-0.4.dist-info/METADATA
splunkhecwriter-0.4.dist-info/WHEEL
splunkhecwriter-0.4.dist-info/top_level.txt
splunkhecwriter-0.4.dist-info/RECORD
