Metadata-Version: 2.1
Name: splunkhecwriter
Version: 0.4
Summary: Library for sending events to Splunk HEC
Home-page: https://github.com/hellqvio86/splunkhecwriter
Author: Olof Hellqvist
Author-email: olof.hellqvist@gmail.com
License: MIT
Download-URL: https://github.com/hellqvio86/splunkhecwriter/archive/v_01.tar.gz
Keywords: splunk,hec
Platform: UNKNOWN
Classifier: Development Status :: 3 - Alpha
Classifier: Intended Audience :: Developers
Classifier: Topic :: Software Development :: Build Tools
Classifier: License :: OSI Approved :: MIT License
Classifier: Programming Language :: Python :: 3
Classifier: Programming Language :: Python :: 3.6
Requires-Python: >=3.6
Requires-Dist: requests
